archi_mcp/__init__.py
archi_mcp/server.py
archi_mcp/archimate/__init__.py
archi_mcp/archimate/generator.py
archi_mcp/archimate/relationships.py
archi_mcp/archimate/validator.py
archi_mcp/archimate/elements/__init__.py
archi_mcp/archimate/elements/application.py
archi_mcp/archimate/elements/base.py
archi_mcp/archimate/elements/business.py
archi_mcp/archimate/elements/implementation.py
archi_mcp/archimate/elements/motivation.py
archi_mcp/archimate/elements/physical.py
archi_mcp/archimate/elements/strategy.py
archi_mcp/archimate/elements/technology.py
archi_mcp/i18n/__init__.py
archi_mcp/i18n/translator.py
archi_mcp/i18n/languages/__init__.py
archi_mcp/i18n/languages/english.py
archi_mcp/i18n/languages/slovak.py
archi_mcp/utils/__init__.py
archi_mcp/utils/exceptions.py
archi_mcp/utils/logging.py
archi_mcp/xml_export/__init__.py
archi_mcp/xml_export/archimate_relationship_matrix.py
archi_mcp/xml_export/exporter.py
archi_mcp/xml_export/liberal_validator.py
archi_mcp/xml_export/relationship_auto_fix.py
archi_mcp/xml_export/templates.py
archi_mcp/xml_export/universal_relationship_fixer.py
archi_mcp/xml_export/validator.py
archi_mcp/xml_export/xml_validator.py
archi_mcp-1.0.0.dist-info/METADATA
archi_mcp-1.0.0.dist-info/WHEEL
archi_mcp-1.0.0.dist-info/entry_points.txt
archi_mcp-1.0.0.dist-info/licenses/LICENSE
archi_mcp-1.0.0.dist-info/RECORD
