Metadata-Version: 2.4
Name: archi-mcp
Version: 1.0.0
Summary: MCP server for generating PlantUML ArchiMate diagrams with comprehensive enterprise architecture modeling support
Project-URL: Homepage, https://github.com/entira/archi-mcp
Project-URL: Repository, https://github.com/entira/archi-mcp
Project-URL: Documentation, https://github.com/entira/archi-mcp#readme
Project-URL: Issues, https://github.com/entira/archi-mcp/issues
Author-email: "Mgr. Patrik Skovajsa" <patrik.skovajsa@gmail.com>
Maintainer-email: "Mgr. Patrik Skovajsa" <patrik.skovajsa@gmail.com>
License: MIT
License-File: LICENSE
Keywords: archimate,diagram-generation,enterprise-architecture,mcp,model-context-protocol,plantuml
Classifier: Development Status :: 5 - Production/Stable
Classifier: Intended Audience :: Developers
Classifier: Intended Audience :: System Administrators
Classifier: License :: OSI Approved :: MIT License
Classifier: Programming Language :: Python :: 3
Classifier: Programming Language :: Python :: 3.11
Classifier: Programming Language :: Python :: 3.12
Classifier: Topic :: Documentation
Classifier: Topic :: Software Development :: Libraries :: Python Modules
Classifier: Topic :: System :: Systems Administration
Requires-Python: >=3.11
Requires-Dist: fastmcp>=2.8.0
Requires-Dist: httpx>=0.25.0
Requires-Dist: loguru>=0.7.0
Requires-Dist: lxml>=5.0.0
Requires-Dist: pillow>=10.0.0
Requires-Dist: pydantic>=2.0.0
Requires-Dist: requests>=2.32.4
Requires-Dist: starlette>=0.28.0
Requires-Dist: typing-extensions>=4.0.0
Requires-Dist: uvicorn>=0.24.0
Provides-Extra: dev
Requires-Dist: black>=23.0.0; extra == 'dev'
Requires-Dist: isort>=5.12.0; extra == 'dev'
Requires-Dist: mypy>=1.5.0; extra == 'dev'
Requires-Dist: pre-commit>=3.0.0; extra == 'dev'
Requires-Dist: pytest-asyncio>=0.21.0; extra == 'dev'
Requires-Dist: pytest-cov>=4.0.0; extra == 'dev'
Requires-Dist: pytest>=7.0.0; extra == 'dev'
Requires-Dist: ruff>=0.1.0; extra == 'dev'
